amazon/__init__.py
amazon/amazon_api.py
AmazonAPIWrapper-0.0.11.dist-info/DESCRIPTION.rst
AmazonAPIWrapper-0.0.11.dist-info/top_level.txt
AmazonAPIWrapper-0.0.11.dist-info/RECORD
AmazonAPIWrapper-0.0.11.dist-info/METADATA
AmazonAPIWrapper-0.0.11.dist-info/WHEEL
AmazonAPIWrapper-0.0.11.dist-info/metadata.json
